README.rst
setup.cfg
setup.py
python_statusio.egg-info/PKG-INFO
python_statusio.egg-info/SOURCES.txt
python_statusio.egg-info/dependency_links.txt
python_statusio.egg-info/requires.txt
python_statusio.egg-info/top_level.txt
statusio/__init__.py
statusio/api.py