Metadata-Version: 1.1
Name: python-statusio
Version: 0.2
Summary: A Python wrapper around the Status.io API
Home-page: https://github.com/statusio/python-statusio
Author: Status.io
Author-email: support@status.io
License: Apache License 2.0
Keywords: status.io api statusio
Platform: UNKNOWN
Classifier: Development Status :: 5 - Production/Stable
Classifier: Intended Audience :: Developers
Classifier: License :: OSI Approved :: Apache Software License
Classifier: Operating System :: OS Independent
Classifier: Topic :: Software Development :: Libraries :: Python Modules
Classifier: Topic :: Internet
Classifier: Programming Language :: Python
Classifier: Programming Language :: Python :: 2
Classifier: Programming Language :: Python :: 2.7
